pyedpiper/__init__.py
pyedpiper/core/__init__.py
pyedpiper/core/common.py
pyedpiper/core/module_loader.py
pyedpiper/core/object_caller.py
pyedpiper/data/__init__.py
pyedpiper/data/datasets.py
pyedpiper/data/imbalanced.py
pyedpiper/data/utils.py
pyedpiper/lightning/__init__.py
pyedpiper/lightning/utils.py
pyedpiper/misc/__init__.py
pyedpiper/misc/random_name.py
pyedpiper/misc/tqdm_handler.py
pyedpiper/modules/__init__.py
pyedpiper/modules/common.py
pyedpiper/modules/extractor.py
pyedpiper/modules/pooling.py
pyedpiper/modules/loss/__init__.py
pyedpiper/modules/loss/cauchy.py
pyedpiper/modules/loss/focal.py
pyedpiper/modules/loss/functional.py
pyedpiper/modules/loss/loss.py
pyedpiper/modules/loss/ohem_nll.py
pyedpiper/modules/loss/reduction.py
pyedpiper/modules/loss/smooth.py
pyedpiper/modules/loss/wing.py
pyedpiper/optim/__init__.py
pyedpiper/optim/radam.py
tests/__init__.py
tests/test_instantiate.py
pyedpiper-0.2.1.dist-info/LICENSE
pyedpiper-0.2.1.dist-info/METADATA
pyedpiper-0.2.1.dist-info/WHEEL
pyedpiper-0.2.1.dist-info/top_level.txt
pyedpiper-0.2.1.dist-info/RECORD
